AUTHORS.rst
CONTRIBUTING.rst
HISTORY.rst
LICENSE
MANIFEST.in
README.rst
setup.cfg
setup.py
docs/Makefile
docs/authors.rst
docs/conf.py
docs/contributing.rst
docs/history.rst
docs/index.rst
docs/installation.rst
docs/make.bat
docs/readme.rst
docs/usage.rst
tests/__init__.py
tests/test_tlcache.py
tlcache/__init__.py
tlcache/cache.py
tlcache/tlcache.py
tlcache.egg-info/PKG-INFO
tlcache.egg-info/SOURCES.txt
tlcache.egg-info/dependency_links.txt
tlcache.egg-info/not-zip-safe
tlcache.egg-info/top_level.txt